zeek_to_sqlite/__init__.py
zeek_to_sqlite/__main__.py
zeek_to_sqlite/args/Args.py
zeek_to_sqlite/args/__init__.py
zeek_to_sqlite/output/Output.py
zeek_to_sqlite/output/__init__.py
zeek_to_sqlite/util/Util.py
zeek_to_sqlite/util/__init__.py
zeek_to_sqlite-1.0.0.dist-info/LICENSE.md
zeek_to_sqlite-1.0.0.dist-info/METADATA
zeek_to_sqlite-1.0.0.dist-info/WHEEL
zeek_to_sqlite-1.0.0.dist-info/entry_points.txt
zeek_to_sqlite-1.0.0.dist-info/top_level.txt
zeek_to_sqlite-1.0.0.dist-info/RECORD
