Metadata-Version: 2.1
Name: zeek_to_sqlite
Version: 1.0.0
Summary: Creates a sqlite db from zeek logs
Home-page: https://github.com/5f0ne/zeek-to-sqlite
Author: 5f0
License: MIT
Classifier: Operating System :: OS Independent 
Classifier: Programming Language :: Python :: 3 
Classifier: License :: OSI Approved :: MIT License 
License-File: LICENSE.md
